mosaicml_streaming-0.13.0.dist-info/licenses/LICENSE
simulation/__init__.py
simulation/launcher.py
simulation/core/__init__.py
simulation/core/create_index.py
simulation/core/last_used_ordered_set.py
simulation/core/main.py
simulation/core/node_tracker.py
simulation/core/shard_downloads.py
simulation/core/shuffle_quality.py
simulation/core/sim_dataset.py
simulation/core/sim_spanner.py
simulation/core/sim_time.py
simulation/core/sim_world.py
simulation/core/utils.py
simulation/core/yaml_processing.py
simulation/interfaces/__init__.py
simulation/interfaces/interface_utils.py
simulation/interfaces/sim_cli.py
simulation/interfaces/sim_script.py
simulation/interfaces/sim_ui.py
simulation/interfaces/widgets.py
streaming/__init__.py
streaming/_version.py
streaming/py.typed
streaming/base/__init__.py
streaming/base/array.py
streaming/base/compression.py
streaming/base/constant.py
streaming/base/dataloader.py
streaming/base/dataset.py
streaming/base/distributed.py
streaming/base/hashing.py
streaming/base/local.py
streaming/base/registry_utils.py
streaming/base/sampling.py
streaming/base/spanner.py
streaming/base/stream.py
streaming/base/util.py
streaming/base/world.py
streaming/base/batching/__init__.py
streaming/base/batching/device_per_stream.py
streaming/base/batching/per_stream.py
streaming/base/batching/random.py
streaming/base/batching/stratified.py
streaming/base/converters/__init__.py
streaming/base/converters/dataframe_to_mds.py
streaming/base/format/__init__.py
streaming/base/format/index.py
streaming/base/format/base/__init__.py
streaming/base/format/base/reader.py
streaming/base/format/base/writer.py
streaming/base/format/json/__init__.py
streaming/base/format/json/encodings.py
streaming/base/format/json/reader.py
streaming/base/format/json/writer.py
streaming/base/format/mds/__init__.py
streaming/base/format/mds/encodings.py
streaming/base/format/mds/reader.py
streaming/base/format/mds/writer.py
streaming/base/format/xsv/__init__.py
streaming/base/format/xsv/encodings.py
streaming/base/format/xsv/reader.py
mosaicml_streaming-0.13.0.dist-info/METADATA
mosaicml_streaming-0.13.0.dist-info/WHEEL
mosaicml_streaming-0.13.0.dist-info/entry_points.txt
mosaicml_streaming-0.13.0.dist-info/top_level.txt
mosaicml_streaming-0.13.0.dist-info/RECORD
